tris/__init__.py
tris/core.py
tris/eclipses.py
tris/filter.py
tris/oc.py
tris/periodic.py
tris/preproc.py
tris/util.py
tris-0.0.1.dist-info/METADATA
tris-0.0.1.dist-info/WHEEL
tris-0.0.1.dist-info/RECORD
