Metadata-Version: 2.1
Name: tris
Version: 0.0.1
Summary: An open-source screening system for Trinary Star Candidates.
Home-page: https://three-body-analysis.github.io/codebase
License: MIT
Keywords: NASA,Kepler,TESS,Astronomy
Author: Vikram Ramanathan
Requires-Python: >=3.8
Classifier: Development Status :: 5 - Production/Stable
Classifier: Intended Audience :: Science/Research
Classifier: License :: OSI Approved :: MIT License
Classifier: Operating System :: OS Independent
Classifier: Programming Language :: Python
Classifier: Programming Language :: Python :: 3
Classifier: Programming Language :: Python :: 3.8
Classifier: Programming Language :: Python :: 3.9
Classifier: Programming Language :: Python :: 3.10
Classifier: Programming Language :: Python :: 3.11
Classifier: Topic :: Scientific/Engineering :: Astronomy
Requires-Dist: astropy (>=5.0)
Requires-Dist: matplotlib (>=3.1)
Requires-Dist: numpy (<=1.24)
Requires-Dist: pandas (>=1.1.4)
Requires-Dist: requests (>=2.22.0)
Requires-Dist: scipy (>=1.7) ; python_version >= "3.8" and python_version < "3.11"
Requires-Dist: tqdm (>=4.25.0)
Requires-Dist: urllib3 (>=1.23) ; python_version >= "3.8" and python_version < "4.0"
Requires-Dist: wotan (==1.10)
Requires-Dist: wquantiles (==0.6)
Project-URL: Bug Tracker, https://github.com/three-body-analysis/codebase/issues
Project-URL: Documentation, https://three-body-analysis.github.io/codebase
Project-URL: Repository, https://github.com/three-body-analysis/codebase
